{
  "job_summary": {
    "objective": "Fix failing pytest test and ensure test isolation",
    "execution_role": "Worker",
    "success_status": "SUCCESS",
    "completion_timestamp": "2025-12-07T16:46:49Z"
  },
  "changes_made": [
    {
      "file": "tests/test_cli.py",
      "change_type": "test_fix",
      "description": "Modified test_command_uses_current_job to use proper test isolation",
      "details": [
        "Added tmp_path parameter to test method",
        "Created isolated jobs directory for testing",
        "Initialized jobs directory properly",
        "Created and selected a test job in the isolated environment",
        "Updated CLI calls to use --jobs-dir parameter",
        "Test now passes by finding the correct current job in isolated state"
      ]
    }
  ],
  "code_changes": {
    "commits": [
      {
        "hash": "0734ad5",
        "type": "fix",
        "subject": "isolate failing test_command_uses_current_job",
        "description": "Add tmp_path parameter for proper test isolation, initialize jobs directory and create test job, pass --jobs-dir parameter to CLI commands, test now correctly finds current job in isolated environment"
      }
    ]
  },
  "testing_results": {
    "pytest_run": true,
    "tests_before_fix": "93 passed, 5 skipped, 1 failed",
    "tests_after_fix": "94 passed, 5 skipped, 0 failed",
    "test_fixed": "test_command_uses_current_job in tests/test_cli.py",
    "all_tests_pass": true
  },
  "subtests_completed": [
    "test_command_uses_current_job - now properly isolated"
  ],
  "subtests_not_completed": [],
  "issues_found": [
    {
      "description": "Test was depending on global ~/.logist/jobs directory state instead of isolated test environment",
      "impact": "Test would fail intermittently based on global job state",
      "resolution": "Fixed by using tmp_path and proper --jobs-dir parameter usage"
    }
  ]
}